{"id":"41267fa5-cb0d-456c-9434-df082dec553a","goal":"Get the title of https://example.com","mode":"research","status":"extracting","current_step":2,"total_steps":2,"step_results":[{"step":{"Action":"navigate","Params":{"action":"navigate","target":"https://example.com","url":"https://example.com"},"Reasoning":"To access the webpage and retrieve its title.","Optional":false},"result":{"Action":"navigate","Success":true,"Element":null,"PageState":{"URL":"https://example.com/","Title":"Example Domain","StatusCode":200},"Duration":141451375,"Error":"","Data":null},"index":0,"duration_ns":0,"cost":0},{"step":{"Action":"extract","Params":{"action":"extract","fields":["title"],"schema":"Extract fields: title","selector":"title"},"Reasoning":"To extract the title of the webpage.","Optional":false},"result":{"Action":"extract","Success":true,"Element":null,"PageState":null,"Duration":659353500,"Error":"","Data":"ewogICJ0aXRsZSI6ICJFeGFtcGxlIERvbWFpbiIKfQ=="},"index":1,"duration_ns":0,"cost":0}],"extracted":[{"title":"Example Domain"}],"extract_count":1,"current_page":0,"total_pages":0,"has_more":false,"last_page_url":"https://example.com/","last_page_title":"Example Domain","last_ax_summary":"","checkpoint_id":"41267fa5-cb0d-456c-9434-df082dec553a","checkpoint_at":"0001-01-01T00:00:00Z","created_at":"2026-03-28T18:15:30.894599Z","updated_at":"2026-03-28T18:15:34.611599Z"}